VoiceAuth/__init__.py
VoiceAuth/animations.py
VoiceAuth/app.py
VoiceAuth/audio_processor.py
VoiceAuth/batch_process.py
VoiceAuth/check_progress.py
VoiceAuth/check_setup.py
VoiceAuth/classify.py
VoiceAuth/feature_extraction.py
VoiceAuth/model.py
VoiceAuth/run.py
VoiceAuth/run_voiceauth.py
VoiceAuth/simple_gui.py
VoiceAuth/simple_model.py
VoiceAuth/simple_startup.py
VoiceAuth/start_application.py
VoiceAuth/startup_animation.py
VoiceAuth/tabs.py
VoiceAuth/ui_components.py
VoiceAuth/utils.py
VoiceAuth/voiceauth.py
VoiceAuth/media/background.png
VoiceAuth/media/logo-no-shadow.png
VoiceAuth/media/text-only-white.png
VoiceAuth/media/voiceauth-full-logo.png
VoiceAuth/media/voiceauth-logo-only.png
VoiceAuth/media/voiceauth-text-only.png
VoiceAuth/output/.gitkeep
VoiceAuth/samples/.gitkeep
voiceauth-1.0.1.dist-info/METADATA
voiceauth-1.0.1.dist-info/WHEEL
voiceauth-1.0.1.dist-info/entry_points.txt
voiceauth-1.0.1.dist-info/top_level.txt
voiceauth-1.0.1.dist-info/RECORD
