Metadata-Version: 2.4
Name: voiceauth
Version: 1.0.1
Summary: AI Voice Detection System
Home-page: https://github.com/zohaiblazuli/VoiceAuth
Author: Zohaib Lazuli
Author-email: zohaibkhanbhs@gmail.com
License: MIT
Project-URL: Homepage, https://github.com/zohaiblazuli/VoiceAuth
Project-URL: Bug Tracker, https://github.com/zohaiblazuli/VoiceAuth/issues
Requires-Python: >=3.8
Requires-Dist: numpy==1.22.4
Requires-Dist: pandas==1.4.3
Requires-Dist: matplotlib==3.5.2
Requires-Dist: seaborn==0.11.2
Requires-Dist: scikit-learn==1.1.2; python_version >= "3.8" and platform_machine != "arm64" and platform_machine != "aarch64"
Requires-Dist: scikit-learn==1.0.2; python_version < "3.8" or platform_machine == "arm64" or platform_machine == "aarch64"
Requires-Dist: librosa==0.9.2
Requires-Dist: sounddevice==0.4.5
Requires-Dist: soundfile==0.10.3.post1
Requires-Dist: pydub==0.25.1
Requires-Dist: noisereduce==2.0.1
Requires-Dist: ffmpeg-python==0.2.0
Requires-Dist: wave==0.0.2
Requires-Dist: numba==0.56.2
Requires-Dist: tqdm==4.64.0
Requires-Dist: concurrent-futures==3.1.1
Requires-Dist: PyQt5==5.15.7
Requires-Dist: PyQt5-sip==12.11.0
Requires-Dist: PyQtWebEngine==5.15.6
Requires-Dist: python-dateutil==2.8.2
Requires-Dist: platformdirs==2.5.2
Requires-Dist: pyinstaller==5.6.2
Requires-Dist: pytest==7.1.2
Requires-Dist: setuptools>=65.5.1
Requires-Dist: wheel>=0.38.0
Requires-Dist: pillow>=9.0.1
Dynamic: author
Dynamic: author-email
Dynamic: home-page
Dynamic: requires-python
